{
    "word": "rotund",
    "date": "20251010",
    "adapter": "merriam-webster",
    "data": [
        {
            "id": "rotund",
            "partOfSpeech": "adjective",
            "text": "marked by roundness: rounded",
            "attributionText": "from Merriam-Webster's Collegiate Dictionary",
            "sourceDictionary": "collegiate",
            "sourceUrl": "https://www.merriam-webster.com/dictionary/rotund",
            "examples": [
                "a master of rotund diction"
            ]
        },
        {
            "id": "rotund",
            "partOfSpeech": "adjective",
            "text": "marked by fullness of sound or cadence: orotund, sonorous",
            "attributionText": "from Merriam-Webster's Collegiate Dictionary",
            "sourceDictionary": "collegiate",
            "sourceUrl": "https://www.merriam-webster.com/dictionary/rotund",
            "examples": [
                "a master of rotund diction"
            ]
        },
        {
            "id": "rotund",
            "partOfSpeech": "adjective",
            "text": "notably plump: chubby",
            "attributionText": "from Merriam-Webster's Collegiate Dictionary",
            "sourceDictionary": "collegiate",
            "sourceUrl": "https://www.merriam-webster.com/dictionary/rotund",
            "examples": [
                "a master of rotund diction"
            ]
        }
    ]
}