{
    "word": "kale",
    "date": "20251113",
    "adapter": "merriam-webster",
    "data": [
        {
            "id": "kale",
            "partOfSpeech": "noun",
            "text": "a hardy cabbage (Brassica oleracea var. acephala) with curled often finely incised leaves that do not form a dense head; also: its leaves used as a vegetable",
            "attributionText": "from Merriam-Webster's Collegiate Dictionary",
            "sourceDictionary": "collegiate",
            "sourceUrl": "https://www.merriam-webster.com/dictionary/kale"
        },
        {
            "id": "kale",
            "partOfSpeech": "noun",
            "text": "cole",
            "attributionText": "from Merriam-Webster's Collegiate Dictionary",
            "sourceDictionary": "collegiate",
            "sourceUrl": "https://www.merriam-webster.com/dictionary/kale"
        },
        {
            "id": "kale",
            "partOfSpeech": "noun",
            "text": "money",
            "attributionText": "from Merriam-Webster's Collegiate Dictionary",
            "sourceDictionary": "collegiate",
            "sourceUrl": "https://www.merriam-webster.com/dictionary/kale"
        },
        {
            "id": "sea kale",
            "partOfSpeech": "noun",
            "text": "a succulent Eurasian perennial herb (Crambe maritima) of the mustard family used as a potherb",
            "attributionText": "from Merriam-Webster's Collegiate Dictionary",
            "sourceDictionary": "collegiate",
            "sourceUrl": "https://www.merriam-webster.com/dictionary/kale"
        }
    ]
}