{
    "word": "alfredo",
    "date": "20250816",
    "adapter": "wordnik",
    "preserveCase": false,
    "data": [
        {
            "partOfSpeech": "noun",
            "text": "Alternative spelling of <xref>Alfredo</xref>.",
            "attributionText": "from Wiktionary, Creative Commons Attribution/Share-Alike License.",
            "sourceDictionary": "wiktionary",
            "sourceUrl": "https://www.wordnik.com/words/alfredo",
            "examples": [],
            "synonyms": [],
            "antonyms": []
        }
    ]
}